quadro/__init__.py
quadro/cli.py
quadro/command.py
quadro/exceptions.py
quadro/mcp.py
quadro/models.py
quadro/renderer.py
quadro/storage.py
qdr-1.0.1.dist-info/METADATA
qdr-1.0.1.dist-info/WHEEL
qdr-1.0.1.dist-info/entry_points.txt
qdr-1.0.1.dist-info/licenses/LICENSE
qdr-1.0.1.dist-info/RECORD
