Metadata-Version: 2.4
Name: qdr
Version: 1.0.1
Summary: Manage your tasks directly from the terminal using markdown
Project-URL: Homepage, https://github.com/spec-driven/quadro
Project-URL: Repository, https://github.com/spec-driven/quadro
Project-URL: Issues, https://github.com/spec-driven/quadro/issues
Project-URL: Changelog, https://github.com/spec-driven/quadro/releases
Author-email: Willian Morais <williandmorais@gmail.com>
License: MIT
License-File: LICENSE
Keywords: cli,markdown,task-manager,terminal
Classifier: Development Status :: 4 - Beta
Classifier: Environment :: Console
Classifier: Intended Audience :: Developers
Classifier: Intended Audience :: End Users/Desktop
Classifier: License :: OSI Approved :: MIT License
Classifier: Operating System :: OS Independent
Classifier: Programming Language :: Python :: 3
Classifier: Programming Language :: Python :: 3.12
Classifier: Programming Language :: Python :: 3.13
Classifier: Topic :: Office/Business
Classifier: Topic :: Software Development :: Bug Tracking
Classifier: Topic :: Utilities
Classifier: Typing :: Typed
Requires-Python: >=3.12
Requires-Dist: click>=8.1.7
Requires-Dist: fastmcp>=2.12.4
Requires-Dist: pydantic>=2.12.0
Requires-Dist: python-frontmatter>=1.1.0
Requires-Dist: rich>=13.7.0
